{"0":{"Jour":1,"OCTOBRE":null,"NOVEMBRE":null,"DECEMBRE":8.0},"1":{"Jour":2,"OCTOBRE":null,"NOVEMBRE":null,"DECEMBRE":1.0},"2":{"Jour":3,"OCTOBRE":null,"NOVEMBRE":null,"DECEMBRE":5.0},"3":{"Jour":4,"OCTOBRE":null,"NOVEMBRE":1.0,"DECEMBRE":null},"4":{"Jour":5,"OCTOBRE":7.0,"NOVEMBRE":3.0,"DECEMBRE":null},"5":{"Jour":6,"OCTOBRE":4.0,"NOVEMBRE":8.0,"DECEMBRE":null},"6":{"Jour":7,"OCTOBRE":6.0,"NOVEMBRE":null,"DECEMBRE":null},"7":{"Jour":8,"OCTOBRE":2.5,"NOVEMBRE":1.5,"DECEMBRE":13.0},"8":{"Jour":9,"OCTOBRE":null,"NOVEMBRE":null,"DECEMBRE":1.0},"9":{"Jour":10,"OCTOBRE":null,"NOVEMBRE":1.5,"DECEMBRE":null},"10":{"Jour":11,"OCTOBRE":null,"NOVEMBRE":1.0,"DECEMBRE":13.0},"11":{"Jour":12,"OCTOBRE":null,"NOVEMBRE":null,"DECEMBRE":2.0},"12":{"Jour":13,"OCTOBRE":null,"NOVEMBRE":2.0,"DECEMBRE":1.0},"13":{"Jour":14,"OCTOBRE":4.0,"NOVEMBRE":4.0,"DECEMBRE":null},"14":{"Jour":15,"OCTOBRE":5.0,"NOVEMBRE":null,"DECEMBRE":11.0},"15":{"Jour":16,"OCTOBRE":4.5,"NOVEMBRE":15.0,"DECEMBRE":6.0},"16":{"Jour":17,"OCTOBRE":1.0,"NOVEMBRE":20.0,"DECEMBRE":2.0},"17":{"Jour":18,"OCTOBRE":null,"NOVEMBRE":null,"DECEMBRE":null},"18":{"Jour":19,"OCTOBRE":null,"NOVEMBRE":22.0,"DECEMBRE":null},"19":{"Jour":20,"OCTOBRE":null,"NOVEMBRE":10.0,"DECEMBRE":null},"20":{"Jour":21,"OCTOBRE":2.5,"NOVEMBRE":7.0,"DECEMBRE":21.0},"21":{"Jour":22,"OCTOBRE":1.0,"NOVEMBRE":null,"DECEMBRE":2.0},"22":{"Jour":23,"OCTOBRE":null,"NOVEMBRE":null,"DECEMBRE":2.0},"23":{"Jour":24,"OCTOBRE":null,"NOVEMBRE":12.0,"DECEMBRE":2.0},"24":{"Jour":25,"OCTOBRE":null,"NOVEMBRE":2.0,"DECEMBRE":7.0},"25":{"Jour":26,"OCTOBRE":null,"NOVEMBRE":null,"DECEMBRE":1.0},"26":{"Jour":27,"OCTOBRE":1.0,"NOVEMBRE":6.0,"DECEMBRE":null},"27":{"Jour":28,"OCTOBRE":1.0,"NOVEMBRE":14.0,"DECEMBRE":null},"28":{"Jour":29,"OCTOBRE":null,"NOVEMBRE":17.0,"DECEMBRE":null},"29":{"Jour":30,"OCTOBRE":null,"NOVEMBRE":14.0,"DECEMBRE":9.0},"30":{"Jour":31,"OCTOBRE":null,"NOVEMBRE":null,"DECEMBRE":1.0}}